cits/__init__.py
cits/methods.py
cits/simulate_timeseries.py
cits-1.1.dist-info/METADATA
cits-1.1.dist-info/WHEEL
cits-1.1.dist-info/top_level.txt
cits-1.1.dist-info/RECORD
