Metadata-Version: 2.1
Name: cits
Version: 1.1
Summary: CITS algorithm for inferring causality from time series data
Home-page: https://github.com/biswasr/CITS
Author: Rahul Biswas
Classifier: Programming Language :: Python :: 3
Classifier: Operating System :: OS Independent
Requires-Python: >=3.6
Requires-Dist: numpy
Requires-Dist: scipy
Requires-Dist: pandas
Requires-Dist: rpy2
Requires-Dist: networkx
